Workbook

Sheet Executive Summary
A1: Walmart Retail Planning & Scenario Model | B1: Walmart Retail Planning & Scenario Model | C1: Walmart Retail Planning & Scenario Model | D1: Walmart Retail Planning & Scenario Model | E1: Walmart Retail Planning & Scenario Model | F1: Walmart Retail Planning & Scenario Model | G1: Walmart Retail Planning & Scenario Model | H1: Walmart Retail Planning & Scenario Model | I1: Walmart Retail Planning & Scenario Model | J1: Walmart Retail Planning & Scenario Model | K1: Walmart Retail Planning & Scenario Model | L1: Walmart Retail Planning & Scenario Model
A2: Walmart Retail Planning & Scenario Model | B2: Walmart Retail Planning & Scenario Model | C2: Walmart Retail Planning & Scenario Model | D2: Walmart Retail Planning & Scenario Model | E2: Walmart Retail Planning & Scenario Model | F2: Walmart Retail Planning & Scenario Model | G2: Walmart Retail Planning & Scenario Model | H2: Walmart Retail Planning & Scenario Model | I2: Walmart Retail Planning & Scenario Model | J2: Walmart Retail Planning & Scenario Model | K2: Walmart Retail Planning & Scenario Model | L2: Walmart Retail Planning & Scenario Model
A3: Actual vs illustrative plan | January-October 2012 | Selected scenario driven by Assumptions
A5: Selected Scenario | B5: =Assumptions!$B$10 -> Base | D5: Model Status | E5: ='Checks & Sources'!$B$12 -> 1
A7: Actual Sales | B7: Actual Sales | D7: Selected Plan | E7: Selected Plan | G7: Plan Variance | H7: Plan Variance | J7: Plan Variance % | K7: Plan Variance %
A8: =SUM('Store Weekly'!$G$4:$G$1938) -> 1.9992655e+09 | D8: =IF(Assumptions!$B$10="Upside",SUM('Store Weekly'!$K$4:$K$1938),IF(Assumptions!$B$10="Downside",SUM('Store Weekly'!$L$4:$L$1938),SUM('Store Weekly'!$J$4:$J$1938))) -> 2.0082227e+09 | G8: =A8-D8 -> -8957199.1 | J8: =IF(D8=0,0,G8/D8) -> -0.0044602619
A11: Forecast Sales | B11: Forecast Sales | D11: Forecast MAE | E11: Forecast MAE | G11: Favorable Stores | H11: Favorable Stores | J11: Unfavorable Stores | K11: Unfavorable Stores
A12: =SUM('Store Weekly'!$I$4:$I$1938) -> 1.9497308e+09 | D12: ='Checks & Sources'!B19 -> 1811.56 | G12: =COUNTIF('Store Performance'!$J$5:$J$49,"Favorable") -> 24 | J12: =COUNTIF('Store Performance'!$J$5:$J$49,"Unfavorable") -> 21
A16: Month | B16: Actual Sales | C16: Selected Plan | D16: Variance | E16: Forecast Sales | F16: Variance %
A17: Jan 2012 | B17: ='Scenario Summary'!B6 -> 1.6880429e+08 | C17: ='Scenario Summary'!J6 -> 1.6857819e+08 | D17: =B17-C17 -> 226102.5 | E17: ='Scenario Summary'!C6 -> 1.6366814e+08 | F17: =IF(C17=0,0,D17/C17) -> 0.0013412322
A18: Feb 2012 | B18: ='Scenario Summary'!B7 -> 1.9194552e+08 | C18: ='Scenario Summary'!J7 -> 1.9189662e+08 | D18: =B18-C18 -> 48895.901 | E18: ='Scenario Summary'!C7 -> 1.863074e+08 | F18: =IF(C18=0,0,D18/C18) -> 0.00025480335
A19: Mar 2012 | B19: ='Scenario Summary'!B8 -> 2.3141508e+08 | C19: ='Scenario Summary'!J8 -> 2.2946785e+08 | D19: =B19-C19 -> 1947227.7 | E19: ='Scenario Summary'!C8 -> 2.2278432e+08 | F19: =IF(C19=0,0,D19/C19) -> 0.0084858407
A20: Apr 2012 | B20: ='Scenario Summary'!B9 -> 1.8883678e+08 | C20: ='Scenario Summary'!J9 -> 1.8853114e+08 | D20: =B20-C20 -> 305637.39 | E20: ='Scenario Summary'!C9 -> 1.8303994e+08 | F20: =IF(C20=0,0,D20/C20) -> 0.0016211507
A21: May 2012 | B21: ='Scenario Summary'!B10 -> 1.8868591e+08 | C21: ='Scenario Summary'!J10 -> 1.8706851e+08 | D21: =B21-C21 -> 1617398.4 | E21: ='Scenario Summary'!C10 -> 1.8161992e+08 | F21: =IF(C21=0,0,D21/C21) -> 0.0086460216
A22: Jun 2012 | B22: ='Scenario Summary'!B11 -> 2.4053628e+08 | C22: ='Scenario Summary'!J11 -> 2.4444895e+08 | D22: =B22-C22 -> -3912674.1 | E22: ='Scenario Summary'!C11 -> 2.3732908e+08 | F22: =IF(C22=0,0,D22/C22) -> -0.016006099
A23: Jul 2012 | B23: ='Scenario Summary'!B12 -> 1.8741516e+08 | C23: ='Scenario Summary'!J12 -> 1.8778633e+08 | D23: =B23-C23 -> -371171.62 | E23: ='Scenario Summary'!C12 -> 1.8231682e+08 | F23: =IF(C23=0,0,D23/C23) -> -0.0019765636
A24: Aug 2012 | B24: ='Scenario Summary'!B13 -> 2.367563e+08 | C24: ='Scenario Summary'!J13 -> 2.409828e+08 | D24: =B24-C24 -> -4226500.9 | E24: ='Scenario Summary'!C13 -> 2.3396388e+08 | F24: =IF(C24=0,0,D24/C24) -> -0.0175386
A25: Sep 2012 | B25: ='Scenario Summary'!B14 -> 1.805536e+08 | C25: ='Scenario Summary'!J14 -> 1.8071492e+08 | D25: =B25-C25 -> -161316.87 | E25: ='Scenario Summary'!C14 -> 1.7545138e+08 | F25: =IF(C25=0,0,D25/C25) -> -0.00089265937
A26: Oct 2012 | B26: ='Scenario Summary'!B15 -> 1.8431656e+08 | C26: ='Scenario Summary'!J15 -> 1.8874736e+08 | D26: =B26-C26 -> -4430797.4 | E26: ='Scenario Summary'!C15 -> 1.8324986e+08 | F26: =IF(C26=0,0,D26/C26) -> -0.023474752

Sheet Assumptions
A1: Walmart Planning Model - Assumptions | B1: Walmart Planning Model - Assumptions | C1: Walmart Planning Model - Assumptions | D1: Walmart Planning Model - Assumptions | E1: Walmart Planning Model - Assumptions | F1: Walmart Planning Model - Assumptions
A2: Walmart Planning Model - Assumptions | B2: Walmart Planning Model - Assumptions | C2: Walmart Planning Model - Assumptions | D2: Walmart Planning Model - Assumptions | E2: Walmart Planning Model - Assumptions | F2: Walmart Planning Model - Assumptions
A3: Blue-font cells are editable. Plans are illustrative and do not represent Walmart internal budgets.
A5: Scenario | B5: Growth Rate | C5: Holiday Uplift | D5: Purpose
A6: Base | B6: 0.03 | C6: 0 | D6: Illustrative prior-year comparable-week benchmark
A7: Upside | B7: 0.05 | C7: 0.01 | D7: Stronger growth and holiday performance
A8: Downside | B8: 0.01 | C8: -0.01 | D8: Slower growth and weaker holiday performance
A10: Selected Scenario | B10: Base
A12: Model convention | B12: Value | C12: Units | D12: Year / As Of | E12: Source | F12: Notes
A13: Evaluation period | B13: Jan 6-Oct 26, 2012 | C13: Weekly | D13: 41208 | E13: Walmart competition data | F13: Matches Power BI report
A14: Planning basis | B14: Prior-year comparable week | C14: Method | D14: 2012 | E14: Project methodology | F14: 52-week lag
A15: Base growth | B15: 0.03 | C15: Rate | D15: 2012 | E15: Project assumption | F15: Editable in B6
A16: Forecast method | B16: Seasonal naive | C16: Method | D16: 2012 | E16: Python pipeline | F16: Selected after chronological testing
A17: Currency | B17: USD | C17: Dollars | D17: 2012 | E17: Source data | F17: No inflation adjustment

Sheet Scenario Summary
A1: 2012 Scenario Summary | B1: 2012 Scenario Summary | C1: 2012 Scenario Summary | D1: 2012 Scenario Summary | E1: 2012 Scenario Summary | F1: 2012 Scenario Summary | G1: 2012 Scenario Summary | H1: 2012 Scenario Summary | I1: 2012 Scenario Summary | J1: 2012 Scenario Summary
A2: 2012 Scenario Summary | B2: 2012 Scenario Summary | C2: 2012 Scenario Summary | D2: 2012 Scenario Summary | E2: 2012 Scenario Summary | F2: 2012 Scenario Summary | G2: 2012 Scenario Summary | H2: 2012 Scenario Summary | I2: 2012 Scenario Summary | J2: 2012 Scenario Summary
A3: January through October 2012 | Formula-driven from store weekly source
A5: Month | B5: Actual Sales | C5: Forecast Sales | D5: Base Plan | E5: Base Variance | F5: Upside Plan | G5: Upside Variance | H5: Downside Plan | I5: Downside Variance | J5: Selected Plan
A6: 40909 | B6: =SUMIFS('Store Weekly'!$G$4:$G$1938,'Store Weekly'!$B$4:$B$1938,A6) -> 1.6880429e+08 | C6: =SUMIFS('Store Weekly'!$I$4:$I$1938,'Store Weekly'!$B$4:$B$1938,A6) -> 1.6366814e+08 | D6: =SUMIFS('Store Weekly'!$J$4:$J$1938,'Store Weekly'!$B$4:$B$1938,A6) -> 1.6857819e+08 | E6: =B6-D6 -> 226102.5 | F6: =SUMIFS('Store Weekly'!$K$4:$K$1938,'Store Weekly'!$B$4:$B$1938,A6) -> 1.7185155e+08 | G6: =B6-F6 -> -3047260.4 | H6: =SUMIFS('Store Weekly'!$L$4:$L$1938,'Store Weekly'!$B$4:$B$1938,A6) -> 1.6530483e+08 | I6: =B6-H6 -> 3499465.4 | J6: =IF(Assumptions!$B$10="Upside",F6,IF(Assumptions!$B$10="Downside",H6,D6)) -> 1.6857819e+08
A7: 40940 | B7: =SUMIFS('Store Weekly'!$G$4:$G$1938,'Store Weekly'!$B$4:$B$1938,A7) -> 1.9194552e+08 | C7: =SUMIFS('Store Weekly'!$I$4:$I$1938,'Store Weekly'!$B$4:$B$1938,A7) -> 1.863074e+08 | D7: =SUMIFS('Store Weekly'!$J$4:$J$1938,'Store Weekly'!$B$4:$B$1938,A7) -> 1.9189662e+08 | E7: =B7-D7 -> 48895.901 | F7: =SUMIFS('Store Weekly'!$K$4:$K$1938,'Store Weekly'!$B$4:$B$1938,A7) -> 1.9609606e+08 | G7: =B7-F7 -> -4150540.7 | H7: =SUMIFS('Store Weekly'!$L$4:$L$1938,'Store Weekly'!$B$4:$B$1938,A7) -> 1.8769718e+08 | I7: =B7-H7 -> 4248332.5 | J7: =IF(Assumptions!$B$10="Upside",F7,IF(Assumptions!$B$10="Downside",H7,D7)) -> 1.9189662e+08
A8: 40969 | B8: =SUMIFS('Store Weekly'!$G$4:$G$1938,'Store Weekly'!$B$4:$B$1938,A8) -> 2.3141508e+08 | C8: =SUMIFS('Store Weekly'!$I$4:$I$1938,'Store Weekly'!$B$4:$B$1938,A8) -> 2.2278432e+08 | D8: =SUMIFS('Store Weekly'!$J$4:$J$1938,'Store Weekly'!$B$4:$B$1938,A8) -> 2.2946785e+08 | E8: =B8-D8 -> 1947227.7 | F8: =SUMIFS('Store Weekly'!$K$4:$K$1938,'Store Weekly'!$B$4:$B$1938,A8) -> 2.3392354e+08 | G8: =B8-F8 -> -2508458.8 | H8: =SUMIFS('Store Weekly'!$L$4:$L$1938,'Store Weekly'!$B$4:$B$1938,A8) -> 2.2501217e+08 | I8: =B8-H8 -> 6402914.1 | J8: =IF(Assumptions!$B$10="Upside",F8,IF(Assumptions!$B$10="Downside",H8,D8)) -> 2.2946785e+08
A9: 41000 | B9: =SUMIFS('Store Weekly'!$G$4:$G$1938,'Store Weekly'!$B$4:$B$1938,A9) -> 1.8883678e+08 | C9: =SUMIFS('Store Weekly'!$I$4:$I$1938,'Store Weekly'!$B$4:$B$1938,A9) -> 1.8303994e+08 | D9: =SUMIFS('Store Weekly'!$J$4:$J$1938,'Store Weekly'!$B$4:$B$1938,A9) -> 1.8853114e+08 | E9: =B9-D9 -> 305637.39 | F9: =SUMIFS('Store Weekly'!$K$4:$K$1938,'Store Weekly'!$B$4:$B$1938,A9) -> 1.9219194e+08 | G9: =B9-F9 -> -3355161.4 | H9: =SUMIFS('Store Weekly'!$L$4:$L$1938,'Store Weekly'!$B$4:$B$1938,A9) -> 1.8487034e+08 | I9: =B9-H9 -> 3966436.2 | J9: =IF(Assumptions!$B$10="Upside",F9,IF(Assumptions!$B$10="Downside",H9,D9)) -> 1.8853114e+08
A10: 41030 | B10: =SUMIFS('Store Weekly'!$G$4:$G$1938,'Store Weekly'!$B$4:$B$1938,A10) -> 1.8868591e+08 | C10: =SUMIFS('Store Weekly'!$I$4:$I$1938,'Store Weekly'!$B$4:$B$1938,A10) -> 1.8161992e+08 | D10: =SUMIFS('Store Weekly'!$J$4:$J$1938,'Store Weekly'!$B$4:$B$1938,A10) -> 1.8706851e+08 | E10: =B10-D10 -> 1617398.4 | F10: =SUMIFS('Store Weekly'!$K$4:$K$1938,'Store Weekly'!$B$4:$B$1938,A10) -> 1.9070091e+08 | G10: =B10-F10 -> -2014999.9 | H10: =SUMIFS('Store Weekly'!$L$4:$L$1938,'Store Weekly'!$B$4:$B$1938,A10) -> 1.8343612e+08 | I10: =B10-H10 -> 5249796.7 | J10: =IF(Assumptions!$B$10="Upside",F10,IF(Assumptions!$B$10="Downside",H10,D10)) -> 1.8706851e+08
A11: 41061 | B11: =SUMIFS('Store Weekly'!$G$4:$G$1938,'Store Weekly'!$B$4:$B$1938,A11) -> 2.4053628e+08 | C11: =SUMIFS('Store Weekly'!$I$4:$I$1938,'Store Weekly'!$B$4:$B$1938,A11) -> 2.3732908e+08 | D11: =SUMIFS('Store Weekly'!$J$4:$J$1938,'Store Weekly'!$B$4:$B$1938,A11) -> 2.4444895e+08 | E11: =B11-D11 -> -3912674.1 | F11: =SUMIFS('Store Weekly'!$K$4:$K$1938,'Store Weekly'!$B$4:$B$1938,A11) -> 2.4919553e+08 | G11: =B11-F11 -> -8659255.7 | H11: =SUMIFS('Store Weekly'!$L$4:$L$1938,'Store Weekly'!$B$4:$B$1938,A11) -> 2.3970237e+08 | I11: =B11-H11 -> 833907.47 | J11: =IF(Assumptions!$B$10="Upside",F11,IF(Assumptions!$B$10="Downside",H11,D11)) -> 2.4444895e+08
A12: 41091 | B12: =SUMIFS('Store Weekly'!$G$4:$G$1938,'Store Weekly'!$B$4:$B$1938,A12) -> 1.8741516e+08 | C12: =SUMIFS('Store Weekly'!$I$4:$I$1938,'Store Weekly'!$B$4:$B$1938,A12) -> 1.8231682e+08 | D12: =SUMIFS('Store Weekly'!$J$4:$J$1938,'Store Weekly'!$B$4:$B$1938,A12) -> 1.8778633e+08 | E12: =B12-D12 -> -371171.62 | F12: =SUMIFS('Store Weekly'!$K$4:$K$1938,'Store Weekly'!$B$4:$B$1938,A12) -> 1.9143266e+08 | G12: =B12-F12 -> -4017508.1 | H12: =SUMIFS('Store Weekly'!$L$4:$L$1938,'Store Weekly'!$B$4:$B$1938,A12) -> 1.8413999e+08 | I12: =B12-H12 -> 3275164.8 | J12: =IF(Assumptions!$B$10="Upside",F12,IF(Assumptions!$B$10="Downside",H12,D12)) -> 1.8778633e+08
A13: 41122 | B13: =SUMIFS('Store Weekly'!$G$4:$G$1938,'Store Weekly'!$B$4:$B$1938,A13) -> 2.367563e+08 | C13: =SUMIFS('Store Weekly'!$I$4:$I$1938,'Store Weekly'!$B$4:$B$1938,A13) -> 2.3396388e+08 | D13: =SUMIFS('Store Weekly'!$J$4:$J$1938,'Store Weekly'!$B$4:$B$1938,A13) -> 2.409828e+08 | E13: =B13-D13 -> -4226500.9 | F13: =SUMIFS('Store Weekly'!$K$4:$K$1938,'Store Weekly'!$B$4:$B$1938,A13) -> 2.4566208e+08 | G13: =B13-F13 -> -8905778.5 | H13: =SUMIFS('Store Weekly'!$L$4:$L$1938,'Store Weekly'!$B$4:$B$1938,A13) -> 2.3630352e+08 | I13: =B13-H13 -> 452776.76 | J13: =IF(Assumptions!$B$10="Upside",F13,IF(Assumptions!$B$10="Downside",H13,D13)) -> 2.409828e+08
A14: 41153 | B14: =SUMIFS('Store Weekly'!$G$4:$G$1938,'Store Weekly'!$B$4:$B$1938,A14) -> 1.805536e+08 | C14: =SUMIFS('Store Weekly'!$I$4:$I$1938,'Store Weekly'!$B$4:$B$1938,A14) -> 1.7545138e+08 | D14: =SUMIFS('Store Weekly'!$J$4:$J$1938,'Store Weekly'!$B$4:$B$1938,A14) -> 1.8071492e+08 | E14: =B14-D14 -> -161316.87 | F14: =SUMIFS('Store Weekly'!$K$4:$K$1938,'Store Weekly'!$B$4:$B$1938,A14) -> 1.8469155e+08 | G14: =B14-F14 -> -4137942.5 | H14: =SUMIFS('Store Weekly'!$L$4:$L$1938,'Store Weekly'!$B$4:$B$1938,A14) -> 1.7673829e+08 | I14: =B14-H14 -> 3815308.8 | J14: =IF(Assumptions!$B$10="Upside",F14,IF(Assumptions!$B$10="Downside",H14,D14)) -> 1.8071492e+08
A15: 41183 | B15: =SUMIFS('Store Weekly'!$G$4:$G$1938,'Store Weekly'!$B$4:$B$1938,A15) -> 1.8431656e+08 | C15: =SUMIFS('Store Weekly'!$I$4:$I$1938,'Store Weekly'!$B$4:$B$1938,A15) -> 1.8324986e+08 | D15: =SUMIFS('Store Weekly'!$J$4:$J$1938,'Store Weekly'!$B$4:$B$1938,A15) -> 1.8874736e+08 | E15: =B15-D15 -> -4430797.4 | F15: =SUMIFS('Store Weekly'!$K$4:$K$1938,'Store Weekly'!$B$4:$B$1938,A15) -> 1.9241236e+08 | G15: =B15-F15 -> -8095794.7 | H15: =SUMIFS('Store Weekly'!$L$4:$L$1938,'Store Weekly'!$B$4:$B$1938,A15) -> 1.8508236e+08 | I15: =B15-H15 -> -765800.15 | J15: =IF(Assumptions!$B$10="Upside",F15,IF(Assumptions!$B$10="Downside",H15,D15)) -> 1.8874736e+08
A16: Total | B16: =SUM(B6:B15) -> 1.9992655e+09 | C16: =SUM(C6:C15) -> 1.9497308e+09 | D16: =SUM(D6:D15) -> 2.0082227e+09 | E16: =SUM(E6:E15) -> -8957199.1 | F16: =SUM(F6:F15) -> 2.0481582e+09 | G16: =SUM(G6:G15) -> -48892701 | H16: =SUM(H6:H15) -> 1.9682872e+09 | I16: =SUM(I6:I15) -> 30978303 | J16: =SUM(J6:J15) -> 2.0082227e+09

Sheet Store Performance
A1: Store Performance by Selected Scenario | B1: Store Performance by Selected Scenario | C1: Store Performance by Selected Scenario | D1: Store Performance by Selected Scenario | E1: Store Performance by Selected Scenario | F1: Store Performance by Selected Scenario | G1: Store Performance by Selected Scenario | H1: Store Performance by Selected Scenario | I1: Store Performance by Selected Scenario | J1: Store Performance by Selected Scenario
A2: Store Performance by Selected Scenario | B2: Store Performance by Selected Scenario | C2: Store Performance by Selected Scenario | D2: Store Performance by Selected Scenario | E2: Store Performance by Selected Scenario | F2: Store Performance by Selected Scenario | G2: Store Performance by Selected Scenario | H2: Store Performance by Selected Scenario | I2: Store Performance by Selected Scenario | J2: Store Performance by Selected Scenario
A4: Store | B4: Type | C4: Size | D4: Actual Sales | E4: Base Plan | F4: Selected Plan | G4: Variance | H4: Variance % | I4: Forecast Sales | J4: Status
A5: 1 | B5: =INDEX('Store Weekly'!$D$4:$D$1938,MATCH(A5,'Store Weekly'!$C$4:$C$1938,0)) -> A | C5: =INDEX('Store Weekly'!$E$4:$E$1938,MATCH(A5,'Store Weekly'!$C$4:$C$1938,0)) -> 151315 | D5: =SUMIFS('Store Weekly'!$G$4:$G$1938,'Store Weekly'!$C$4:$C$1938,A5) -> 68194164 | E5: =SUMIFS('Store Weekly'!$J$4:$J$1938,'Store Weekly'!$C$4:$C$1938,A5) -> 66973769 | F5: =IF(Assumptions!$B$10="Upside",SUMIFS('Store Weekly'!$K$4:$K$1938,'Store Weekly'!$C$4:$C$1938,A5),IF(Assumptions!$B$10="Downside",SUMIFS('Store Weekly'!$L$4:$L$1938,'Store Weekly'!$C$4:$C$1938,A5),E5)) -> 66973769 | G5: =D5-F5 -> 1220395.8 | H5: =IF(F5=0,0,G5/F5) -> 0.018221997 | I5: =SUMIFS('Store Weekly'!$I$4:$I$1938,'Store Weekly'!$C$4:$C$1938,A5) -> 65023076 | J5: =IF(G5>=0,"Favorable","Unfavorable") -> Favorable
A6: 2 | B6: =INDEX('Store Weekly'!$D$4:$D$1938,MATCH(A6,'Store Weekly'!$C$4:$C$1938,0)) -> A | C6: =INDEX('Store Weekly'!$E$4:$E$1938,MATCH(A6,'Store Weekly'!$C$4:$C$1938,0)) -> 202307 | D6: =SUMIFS('Store Weekly'!$G$4:$G$1938,'Store Weekly'!$C$4:$C$1938,A6) -> 81491215 | E6: =SUMIFS('Store Weekly'!$J$4:$J$1938,'Store Weekly'!$C$4:$C$1938,A6) -> 80783042 | F6: =IF(Assumptions!$B$10="Upside",SUMIFS('Store Weekly'!$K$4:$K$1938,'Store Weekly'!$C$4:$C$1938,A6),IF(Assumptions!$B$10="Downside",SUMIFS('Store Weekly'!$L$4:$L$1938,'Store Weekly'!$C$4:$C$1938,A6),E6)) -> 80783042 | G6: =D6-F6 -> 708172.88 | H6: =IF(F6=0,0,G6/F6) -> 0.0087663557 | I6: =SUMIFS('Store Weekly'!$I$4:$I$1938,'Store Weekly'!$C$4:$C$1938,A6) -> 78430138 | J6: =IF(G6>=0,"Favorable","Unfavorable") -> Favorable
A7: 3 | B7: =INDEX('Store Weekly'!$D$4:$D$1938,MATCH(A7,'Store Weekly'!$C$4:$C$1938,0)) -> B | C7: =INDEX('Store Weekly'!$E$4:$E$1938,MATCH(A7,'Store Weekly'!$C$4:$C$1938,0)) -> 37392 | D7: =SUMIFS('Store Weekly'!$G$4:$G$1938,'Store Weekly'!$C$4:$C$1938,A7) -> 18020529 | E7: =SUMIFS('Store Weekly'!$J$4:$J$1938,'Store Weekly'!$C$4:$C$1938,A7) -> 17074996 | F7: =IF(Assumptions!$B$10="Upside",SUMIFS('Store Weekly'!$K$4:$K$1938,'Store Weekly'!$C$4:$C$1938,A7),IF(Assumptions!$B$10="Downside",SUMIFS('Store Weekly'!$L$4:$L$1938,'Store Weekly'!$C$4:$C$1938,A7),E7)) -> 17074996 | G7: =D7-F7 -> 945532.89 | H7: =IF(F7=0,0,G7/F7) -> 0.055375291 | I7: =SUMIFS('Store Weekly'!$I$4:$I$1938,'Store Weekly'!$C$4:$C$1938,A7) -> 16577666 | J7: =IF(G7>=0,"Favorable","Unfavorable") -> Favorable
A8: 4 | B8: =INDEX('Store Weekly'!$D$4:$D$1938,MATCH(A8,'Store Weekly'!$C$4:$C$1938,0)) -> A | C8: =INDEX('Store Weekly'!$E$4:$E$1938,MATCH(A8,'Store Weekly'!$C$4:$C$1938,0)) -> 205863 | D8: =SUMIFS('Store Weekly'!$G$4:$G$1938,'Store Weekly'!$C$4:$C$1938,A8) -> 92760693 | E8: =SUMIFS('Store Weekly'!$J$4:$J$1938,'Store Weekly'!$C$4:$C$1938,A8) -> 90860445 | F8: =IF(Assumptions!$B$10="Upside",SUMIFS('Store Weekly'!$K$4:$K$1938,'Store Weekly'!$C$4:$C$1938,A8),IF(Assumptions!$B$10="Downside",SUMIFS('Store Weekly'!$L$4:$L$1938,'Store Weekly'!$C$4:$C$1938,A8),E8)) -> 90860445 | G8: =D8-F8 -> 1900247.7 | H8: =IF(F8=0,0,G8/F8) -> 0.020913915 | I8: =SUMIFS('Store Weekly'!$I$4:$I$1938,'Store Weekly'!$C$4:$C$1938,A8) -> 88214024 | J8: =IF(G8>=0,"Favorable","Unfavorable") -> Favorable
A9: 5 | B9: =INDEX('Store Weekly'!$D$4:$D$1938,MATCH(A9,'Store Weekly'!$C$4:$C$1938,0)) -> B | C9: =INDEX('Store Weekly'!$E$4:$E$1938,MATCH(A9,'Store Weekly'!$C$4:$C$1938,0)) -> 34875 | D9: =SUMIFS('Store Weekly'!$G$4:$G$1938,'Store Weekly'!$C$4:$C$1938,A9) -> 14163908 | E9: =SUMIFS('Store Weekly'!$J$4:$J$1938,'Store Weekly'!$C$4:$C$1938,A9) -> 13439207 | F9: =IF(Assumptions!$B$10="Upside",SUMIFS('Store Weekly'!$K$4:$K$1938,'Store Weekly'!$C$4:$C$1938,A9),IF(Assumptions!$B$10="Downside",SUMIFS('Store Weekly'!$L$4:$L$1938,'Store Weekly'!$C$4:$C$1938,A9),E9)) -> 13439207 | G9: =D9-F9 -> 724700.93 | H9: =IF(F9=0,0,G9/F9) -> 0.05392438 | I9: =SUMIFS('Store Weekly'!$I$4:$I$1938,'Store Weekly'!$C$4:$C$1938,A9) -> 13047774 | J9: =IF(G9>=0,"Favorable","Unfavorable") -> Favorable
A10: 6 | B10: =INDEX('Store Weekly'!$D$4:$D$1938,MATCH(A10,'Store Weekly'!$C$4:$C$1938,0)) -> A | C10: =INDEX('Store Weekly'!$E$4:$E$1938,MATCH(A10,'Store Weekly'!$C$4:$C$1938,0)) -> 202505 | D10: =SUMIFS('Store Weekly'!$G$4:$G$1938,'Store Weekly'!$C$4:$C$1938,A10) -> 66304295 | E10: =SUMIFS('Store Weekly'!$J$4:$J$1938,'Store Weekly'!$C$4:$C$1938,A10) -> 65739486 | F10: =IF(Assumptions!$B$10="Upside",SUMIFS('Store Weekly'!$K$4:$K$1938,'Store Weekly'!$C$4:$C$1938,A10),IF(Assumptions!$B$10="Downside",SUMIFS('Store Weekly'!$L$4:$L$1938,'Store Weekly'!$C$4:$C$1938,A10),E10)) -> 65739486 | G10: =D10-F10 -> 564808.9 | H10: =IF(F10=0,0,G10/F10) -> 0.0085916233 | I10: =SUMIFS('Store Weekly'!$I$4:$I$1938,'Store Weekly'!$C$4:$C$1938,A10) -> 63824744 | J10: =IF(G10>=0,"Favorable","Unfavorable") -> Favorable
A11: 7 | B11: =INDEX('Store Weekly'!$D$4:$D$1938,MATCH(A11,'Store Weekly'!$C$4:$C$1938,0)) -> B | C11: =INDEX('Store Weekly'!$E$4:$E$1938,MATCH(A11,'Store Weekly'!$C$4:$C$1938,0)) -> 70713 | D11: =SUMIFS('Store Weekly'!$G$4:$G$1938,'Store Weekly'!$C$4:$C$1938,A11) -> 25309824 | E11: =SUMIFS('Store Weekly'!$J$4:$J$1938,'Store Weekly'!$C$4:$C$1938,A11) -> 24932556 | F11: =IF(Assumptions!$B$10="Upside",SUMIFS('Store Weekly'!$K$4:$K$1938,'Store Weekly'!$C$4:$C$1938,A11),IF(Assumptions!$B$10="Downside",SUMIFS('Store Weekly'!$L$4:$L$1938,'Store Weekly'!$C$4:$C$1938,A11),E11)) -> 24932556 | G11: =D11-F11 -> 377267.64 | H11: =IF(F11=0,0,G11/F11) -> 0.015131526 | I11: =SUMIFS('Store Weekly'!$I$4:$I$1938,'Store Weekly'!$C$4:$C$1938,A11) -> 24206365 | J11: =IF(G11>=0,"Favorable","Unfavorable") -> Favorable
A12: 8 | B12: =INDEX('Store Weekly'!$D$4:$D$1938,MATCH(A12,'Store Weekly'!$C$4:$C$1938,0)) -> A | C12: =INDEX('Store Weekly'!$E$4:$E$1938,MATCH(A12,'Store Weekly'!$C$4:$C$1938,0)) -> 155078 | D12: =SUMIFS('Store Weekly'!$G$4:$G$1938,'Store Weekly'!$C$4:$C$1938,A12) -> 39223988 | E12: =SUMIFS('Store Weekly'!$J$4:$J$1938,'Store Weekly'!$C$4:$C$1938,A12) -> 39167240 | F12: =IF(Assumptions!$B$10="Upside",SUMIFS('Store Weekly'!$K$4:$K$1938,'Store Weekly'!$C$4:$C$1938,A12),IF(Assumptions!$B$10="Downside",SUMIFS('Store Weekly'!$L$4:$L$1938,'Store Weekly'!$C$4:$C$1938,A12),E12)) -> 39167240 | G12: =D12-F12 -> 56747.51 | H12: =IF(F12=0,0,G12/F12) -> 0.0014488514 | I12: =SUMIFS('Store Weekly'!$I$4:$I$1938,'Store Weekly'!$C$4:$C$1938,A12) -> 38026447 | J12: =IF(G12>=0,"Favorable","Unfavorable") -> Favorable
A13: 9 | B13: =INDEX('Store Weekly'!$D$4:$D$1938,MATCH(A13,'Store Weekly'!$C$4:$C$1938,0)) -> B | C13: =INDEX('Store Weekly'!$E$4:$E$1938,MATCH(A13,'Store Weekly'!$C$4:$C$1938,0)) -> 125833 | D13: =SUMIFS('Store Weekly'!$G$4:$G$1938,'Store Weekly'!$C$4:$C$1938,A13) -> 23952884 | E13: =SUMIFS('Store Weekly'!$J$4:$J$1938,'Store Weekly'!$C$4:$C$1938,A13) -> 23406174 | F13: =IF(Assumptions!$B$10="Upside",SUMIFS('Store Weekly'!$K$4:$K$1938,'Store Weekly'!$C$4:$C$1938,A13),IF(Assumptions!$B$10="Downside",SUMIFS('Store Weekly'!$L$4:$L$1938,'Store Weekly'!$C$4:$C$1938,A13),E13)) -> 23406174 | G13: =D13-F13 -> 546709.9 | H13: =IF(F13=0,0,G13/F13) -> 0.023357508 | I13: =SUMIFS('Store Weekly'!$I$4:$I$1938,'Store Weekly'!$C$4:$C$1938,A13) -> 22724441 | J13: =IF(G13>=0,"Favorable","Unfavorable") -> Favorable
A14: 10 | B14: =INDEX('Store Weekly'!$D$4:$D$1938,MATCH(A14,'Store Weekly'!$C$4:$C$1938,0)) -> B | C14: =INDEX('Store Weekly'!$E$4:$E$1938,MATCH(A14,'Store Weekly'!$C$4:$C$1938,0)) -> 126512 | D14: =SUMIFS('Store Weekly'!$G$4:$G$1938,'Store Weekly'!$C$4:$C$1938,A14) -> 78226262 | E14: =SUMIFS('Store Weekly'!$J$4:$J$1938,'Store Weekly'!$C$4:$C$1938,A14) -> 79973765 | F14: =IF(Assumptions!$B$10="Upside",SUMIFS('Store Weekly'!$K$4:$K$1938,'Store Weekly'!$C$4:$C$1938,A14),IF(Assumptions!$B$10="Downside",SUMIFS('Store Weekly'!$L$4:$L$1938,'Store Weekly'!$C$4:$C$1938,A14),E14)) -> 79973765 | G14: =D14-F14 -> -1747502.3 | H14: =IF(F14=0,0,G14/F14) -> -0.021850944 | I14: =SUMIFS('Store Weekly'!$I$4:$I$1938,'Store Weekly'!$C$4:$C$1938,A14) -> 77644432 | J14: =IF(G14>=0,"Favorable","Unfavorable") -> Unfavorable
A15: 11 | B15: =INDEX('Store Weekly'!$D$4:$D$1938,MATCH(A15,'Store Weekly'!$C$4:$C$1938,0)) -> A | C15: =INDEX('Store Weekly'!$E$4:$E$1938,MATCH(A15,'Store Weekly'!$C$4:$C$1938,0)) -> 207499 | D15: =SUMIFS('Store Weekly'!$G$4:$G$1938,'Store Weekly'!$C$4:$C$1938,A15) -> 58134260 | E15: =SUMIFS('Store Weekly'!$J$4:$J$1938,'Store Weekly'!$C$4:$C$1938,A15) -> 57823130 | F15: =IF(Assumptions!$B$10="Upside",SUMIFS('Store Weekly'!$K$4:$K$1938,'Store Weekly'!$C$4:$C$1938,A15),IF(Assumptions!$B$10="Downside",SUMIFS('Store Weekly'!$L$4:$L$1938,'Store Weekly'!$C$4:$C$1938,A15),E15)) -> 57823130 | G15: =D15-F15 -> 311129.63 | H15: =IF(F15=0,0,G15/F15) -> 0.0053807123 | I15: =SUMIFS('Store Weekly'!$I$4:$I$1938,'Store Weekly'!$C$4:$C$1938,A15) -> 56138961 | J15: =IF(G15>=0,"Favorable","Unfavorable") -> Favorable
A16: 12 | B16: =INDEX('Store Weekly'!$D$4:$D$1938,MATCH(A16,'Store Weekly'!$C$4:$C$1938,0)) -> B | C16: =INDEX('Store Weekly'!$E$4:$E$1938,MATCH(A16,'Store Weekly'!$C$4:$C$1938,0)) -> 112238 | D16: =SUMIFS('Store Weekly'!$G$4:$G$1938,'Store Weekly'!$C$4:$C$1938,A16) -> 43325026 | E16: =SUMIFS('Store Weekly'!$J$4:$J$1938,'Store Weekly'!$C$4:$C$1938,A16) -> 42832236 | F16: =IF(Assumptions!$B$10="Upside",SUMIFS('Store Weekly'!$K$4:$K$1938,'Store Weekly'!$C$4:$C$1938,A16),IF(Assumptions!$B$10="Downside",SUMIFS('Store Weekly'!$L$4:$L$1938,'Store Weekly'!$C$4:$C$1938,A16),E16)) -> 42832236 | G16: =D16-F16 -> 492789.31 | H16: =IF(F16=0,0,G16/F16) -> 0.011505104 | I16: =SUMIFS('Store Weekly'!$I$4:$I$1938,'Store Weekly'!$C$4:$C$1938,A16) -> 41584696 | J16: =IF(G16>=0,"Favorable","Unfavorable") -> Favorable
... A49: 45 | B49: =INDEX('Store Weekly'!$D$4:$D$1938,MATCH(A49,'Store Weekly'!$C$4:$C$1938,0)) -> B | C49: =INDEX('Store Weekly'!$E$4:$E$1938,MATCH(A49,'Store Weekly'!$C$4:$C$1938,0)) -> 118221 | D49: =SUMIFS('Store Weekly'!$G$4:$G$1938,'Store Weekly'!$C$4:$C$1938,A49) -> 32711746 | E49: =SUMIFS('Store Weekly'!$J$4:$J$1938,'Store Weekly'!$C$4:$C$1938,A49) -> 33210854 | F49: =IF(Assumptions!$B$10="Upside",SUMIFS('Store Weekly'!$K$4:$K$1938,'Store Weekly'!$C$4:$C$1938,A49),IF(Assumptions!$B$10="Downside",SUMIFS('Store Weekly'!$L$4:$L$1938,'Store Weekly'!$C$4:$C$1938,A49),E49)) -> 33210854 | G49: =D49-F49 -> -499108.12 | H49: =IF(F49=0,0,G49/F49) -> -0.015028464 | I49: =SUMIFS('Store Weekly'!$I$4:$I$1938,'Store Weekly'!$C$4:$C$1938,A49) -> 32243548 | J49: =IF(G49>=0,"Favorable","Unfavorable") -> Unfavorable

Sheet Department Performance
A1: Department Performance by Selected Scenario | B1: Department Performance by Selected Scenario | C1: Department Performance by Selected Scenario | D1: Department Performance by Selected Scenario | E1: Department Performance by Selected Scenario | F1: Department Performance by Selected Scenario | G1: Department Performance by Selected Scenario | H1: Department Performance by Selected Scenario
A2: Department Performance by Selected Scenario | B2: Department Performance by Selected Scenario | C2: Department Performance by Selected Scenario | D2: Department Performance by Selected Scenario | E2: Department Performance by Selected Scenario | F2: Department Performance by Selected Scenario | G2: Department Performance by Selected Scenario | H2: Department Performance by Selected Scenario
A4: Department | B4: Actual Sales | C4: Base Plan | D4: Selected Plan | E4: Variance | F4: Variance % | G4: Forecast Sales | H4: Status
A5: 1 | B5: =SUMIFS('Department Weekly'!$E$4:$E$3247,'Department Weekly'!$C$4:$C$3247,A5) -> 35445928 | C5: =SUMIFS('Department Weekly'!$H$4:$H$3247,'Department Weekly'!$C$4:$C$3247,A5) -> 35442809 | D5: =IF(Assumptions!$B$10="Upside",SUMIFS('Department Weekly'!$I$4:$I$3247,'Department Weekly'!$C$4:$C$3247,A5),IF(Assumptions!$B$10="Downside",SUMIFS('Department Weekly'!$J$4:$J$3247,'Department Weekly'!$C$4:$C$3247,A5),C5)) -> 35442809 | E5: =B5-D5 -> 3118.4456 | F5: =IF(D5=0,0,E5/D5) -> 8.7985283e-05 | G5: =SUMIFS('Department Weekly'!$G$4:$G$3247,'Department Weekly'!$C$4:$C$3247,A5) -> 34410494 | H5: =IF(E5>=0,"Favorable","Unfavorable") -> Favorable
A6: 2 | B6: =SUMIFS('Department Weekly'!$E$4:$E$3247,'Department Weekly'!$C$4:$C$3247,A6) -> 85052986 | C6: =SUMIFS('Department Weekly'!$H$4:$H$3247,'Department Weekly'!$C$4:$C$3247,A6) -> 85468722 | D6: =IF(Assumptions!$B$10="Upside",SUMIFS('Department Weekly'!$I$4:$I$3247,'Department Weekly'!$C$4:$C$3247,A6),IF(Assumptions!$B$10="Downside",SUMIFS('Department Weekly'!$J$4:$J$3247,'Department Weekly'!$C$4:$C$3247,A6),C6)) -> 85468722 | E6: =B6-D6 -> -415736.37 | F6: =IF(D6=0,0,E6/D6) -> -0.0048641931 | G6: =SUMIFS('Department Weekly'!$G$4:$G$3247,'Department Weekly'!$C$4:$C$3247,A6) -> 82979342 | H6: =IF(E6>=0,"Favorable","Unfavorable") -> Unfavorable
A7: 3 | B7: =SUMIFS('Department Weekly'!$E$4:$E$3247,'Department Weekly'!$C$4:$C$3247,A7) -> 23783097 | C7: =SUMIFS('Department Weekly'!$H$4:$H$3247,'Department Weekly'!$C$4:$C$3247,A7) -> 23711323 | D7: =IF(Assumptions!$B$10="Upside",SUMIFS('Department Weekly'!$I$4:$I$3247,'Department Weekly'!$C$4:$C$3247,A7),IF(Assumptions!$B$10="Downside",SUMIFS('Department Weekly'!$J$4:$J$3247,'Department Weekly'!$C$4:$C$3247,A7),C7)) -> 23711323 | E7: =B7-D7 -> 71773.569 | F7: =IF(D7=0,0,E7/D7) -> 0.0030269745 | G7: =SUMIFS('Department Weekly'!$G$4:$G$3247,'Department Weekly'!$C$4:$C$3247,A7) -> 23020702 | H7: =IF(E7>=0,"Favorable","Unfavorable") -> Favorable
A8: 4 | B8: =SUMIFS('Department Weekly'!$E$4:$E$3247,'Department Weekly'!$C$4:$C$3247,A8) -> 51003352 | C8: =SUMIFS('Department Weekly'!$H$4:$H$3247,'Department Weekly'!$C$4:$C$3247,A8) -> 51042424 | D8: =IF(Assumptions!$B$10="Upside",SUMIFS('Department Weekly'!$I$4:$I$3247,'Department Weekly'!$C$4:$C$3247,A8),IF(Assumptions!$B$10="Downside",SUMIFS('Department Weekly'!$J$4:$J$3247,'Department Weekly'!$C$4:$C$3247,A8),C8)) -> 51042424 | E8: =B8-D8 -> -39071.862 | F8: =IF(D8=0,0,E8/D8) -> -0.00076547818 | G8: =SUMIFS('Department Weekly'!$G$4:$G$3247,'Department Weekly'!$C$4:$C$3247,A8) -> 49555752 | H8: =IF(E8>=0,"Favorable","Unfavorable") -> Unfavorable
A9: 5 | B9: =SUMIFS('Department Weekly'!$E$4:$E$3247,'Department Weekly'!$C$4:$C$3247,A9) -> 33452136 | C9: =SUMIFS('Department Weekly'!$H$4:$H$3247,'Department Weekly'!$C$4:$C$3247,A9) -> 35861695 | D9: =IF(Assumptions!$B$10="Upside",SUMIFS('Department Weekly'!$I$4:$I$3247,'Department Weekly'!$C$4:$C$3247,A9),IF(Assumptions!$B$10="Downside",SUMIFS('Department Weekly'!$J$4:$J$3247,'Department Weekly'!$C$4:$C$3247,A9),C9)) -> 35861695 | E9: =B9-D9 -> -2409558.9 | F9: =IF(D9=0,0,E9/D9) -> -0.067190323 | G9: =SUMIFS('Department Weekly'!$G$4:$G$3247,'Department Weekly'!$C$4:$C$3247,A9) -> 34817179 | H9: =IF(E9>=0,"Favorable","Unfavorable") -> Unfavorable
A10: 6 | B10: =SUMIFS('Department Weekly'!$E$4:$E$3247,'Department Weekly'!$C$4:$C$3247,A10) -> 5955777.5 | C10: =SUMIFS('Department Weekly'!$H$4:$H$3247,'Department Weekly'!$C$4:$C$3247,A10) -> 7459647.6 | D10: =IF(Assumptions!$B$10="Upside",SUMIFS('Department Weekly'!$I$4:$I$3247,'Department Weekly'!$C$4:$C$3247,A10),IF(Assumptions!$B$10="Downside",SUMIFS('Department Weekly'!$J$4:$J$3247,'Department Weekly'!$C$4:$C$3247,A10),C10)) -> 7459647.6 | E10: =B10-D10 -> -1503870.1 | F10: =IF(D10=0,0,E10/D10) -> -0.20160069 | G10: =SUMIFS('Department Weekly'!$G$4:$G$3247,'Department Weekly'!$C$4:$C$3247,A10) -> 7242376.3 | H10: =IF(E10>=0,"Favorable","Unfavorable") -> Unfavorable
A11: 7 | B11: =SUMIFS('Department Weekly'!$E$4:$E$3247,'Department Weekly'!$C$4:$C$3247,A11) -> 37849581 | C11: =SUMIFS('Department Weekly'!$H$4:$H$3247,'Department Weekly'!$C$4:$C$3247,A11) -> 38110642 | D11: =IF(Assumptions!$B$10="Upside",SUMIFS('Department Weekly'!$I$4:$I$3247,'Department Weekly'!$C$4:$C$3247,A11),IF(Assumptions!$B$10="Downside",SUMIFS('Department Weekly'!$J$4:$J$3247,'Department Weekly'!$C$4:$C$3247,A11),C11)) -> 38110642 | E11: =B11-D11 -> -261061.09 | F11: =IF(D11=0,0,E11/D11) -> -0.0068500838 | G11: =SUMIFS('Department Weekly'!$G$4:$G$3247,'Department Weekly'!$C$4:$C$3247,A11) -> 37000623 | H11: =IF(E11>=0,"Favorable","Unfavorable") -> Unfavorable
A12: 8 | B12: =SUMIFS('Department Weekly'!$E$4:$E$3247,'Department Weekly'!$C$4:$C$3247,A12) -> 58876084 | C12: =SUMIFS('Department Weekly'!$H$4:$H$3247,'Department Weekly'!$C$4:$C$3247,A12) -> 58964252 | D12: =IF(Assumptions!$B$10="Upside",SUMIFS('Department Weekly'!$I$4:$I$3247,'Department Weekly'!$C$4:$C$3247,A12),IF(Assumptions!$B$10="Downside",SUMIFS('Department Weekly'!$J$4:$J$3247,'Department Weekly'!$C$4:$C$3247,A12),C12)) -> 58964252 | E12: =B12-D12 -> -88167.795 | F12: =IF(D12=0,0,E12/D12) -> -0.0014952754 | G12: =SUMIFS('Department Weekly'!$G$4:$G$3247,'Department Weekly'!$C$4:$C$3247,A12) -> 57246846 | H12: =IF(E12>=0,"Favorable","Unfavorable") -> Unfavorable
A13: 9 | B13: =SUMIFS('Department Weekly'!$E$4:$E$3247,'Department Weekly'!$C$4:$C$3247,A13) -> 40182176 | C13: =SUMIFS('Department Weekly'!$H$4:$H$3247,'Department Weekly'!$C$4:$C$3247,A13) -> 38521873 | D13: =IF(Assumptions!$B$10="Upside",SUMIFS('Department Weekly'!$I$4:$I$3247,'Department Weekly'!$C$4:$C$3247,A13),IF(Assumptions!$B$10="Downside",SUMIFS('Department Weekly'!$J$4:$J$3247,'Department Weekly'!$C$4:$C$3247,A13),C13)) -> 38521873 | E13: =B13-D13 -> 1660303.1 | F13: =IF(D13=0,0,E13/D13) -> 0.04310027 | G13: =SUMIFS('Department Weekly'!$G$4:$G$3247,'Department Weekly'!$C$4:$C$3247,A13) -> 37399877 | H13: =IF(E13>=0,"Favorable","Unfavorable") -> Favorable
A14: 10 | B14: =SUMIFS('Department Weekly'!$E$4:$E$3247,'Department Weekly'!$C$4:$C$3247,A14) -> 35790073 | C14: =SUMIFS('Department Weekly'!$H$4:$H$3247,'Department Weekly'!$C$4:$C$3247,A14) -> 36107933 | D14: =IF(Assumptions!$B$10="Upside",SUMIFS('Department Weekly'!$I$4:$I$3247,'Department Weekly'!$C$4:$C$3247,A14),IF(Assumptions!$B$10="Downside",SUMIFS('Department Weekly'!$J$4:$J$3247,'Department Weekly'!$C$4:$C$3247,A14),C14)) -> 36107933 | E14: =B14-D14 -> -317860.62 | F14: =IF(D14=0,0,E14/D14) -> -0.0088030687 | G14: =SUMIFS('Department Weekly'!$G$4:$G$3247,'Department Weekly'!$C$4:$C$3247,A14) -> 35056246 | H14: =IF(E14>=0,"Favorable","Unfavorable") -> Unfavorable
A15: 11 | B15: =SUMIFS('Department Weekly'!$E$4:$E$3247,'Department Weekly'!$C$4:$C$3247,A15) -> 27336094 | C15: =SUMIFS('Department Weekly'!$H$4:$H$3247,'Department Weekly'!$C$4:$C$3247,A15) -> 27892739 | D15: =IF(Assumptions!$B$10="Upside",SUMIFS('Department Weekly'!$I$4:$I$3247,'Department Weekly'!$C$4:$C$3247,A15),IF(Assumptions!$B$10="Downside",SUMIFS('Department Weekly'!$J$4:$J$3247,'Department Weekly'!$C$4:$C$3247,A15),C15)) -> 27892739 | E15: =B15-D15 -> -556645.19 | F15: =IF(D15=0,0,E15/D15) -> -0.019956634 | G15: =SUMIFS('Department Weekly'!$G$4:$G$3247,'Department Weekly'!$C$4:$C$3247,A15) -> 27080329 | H15: =IF(E15>=0,"Favorable","Unfavorable") -> Unfavorable
A16: 12 | B16: =SUMIFS('Department Weekly'!$E$4:$E$3247,'Department Weekly'!$C$4:$C$3247,A16) -> 8187798.5 | C16: =SUMIFS('Department Weekly'!$H$4:$H$3247,'Department Weekly'!$C$4:$C$3247,A16) -> 8250680.5 | D16: =IF(Assumptions!$B$10="Upside",SUMIFS('Department Weekly'!$I$4:$I$3247,'Department Weekly'!$C$4:$C$3247,A16),IF(Assumptions!$B$10="Downside",SUMIFS('Department Weekly'!$J$4:$J$3247,'Department Weekly'!$C$4:$C$3247,A16),C16)) -> 8250680.5 | E16: =B16-D16 -> -62881.931 | F16: =IF(D16=0,0,E16/D16) -> -0.0076214236 | G16: =SUMIFS('Department Weekly'!$G$4:$G$3247,'Department Weekly'!$C$4:$C$3247,A16) -> 8010369.4 | H16: =IF(E16>=0,"Favorable","Unfavorable") -> Unfavorable
... A82: 99 | B82: =SUMIFS('Department Weekly'!$E$4:$E$3247,'Department Weekly'!$C$4:$C$3247,A82) -> 17272.38 | C82: =SUMIFS('Department Weekly'!$H$4:$H$3247,'Department Weekly'!$C$4:$C$3247,A82) -> 30927.975 | D82: =IF(Assumptions!$B$10="Upside",SUMIFS('Department Weekly'!$I$4:$I$3247,'Department Weekly'!$C$4:$C$3247,A82),IF(Assumptions!$B$10="Downside",SUMIFS('Department Weekly'!$J$4:$J$3247,'Department Weekly'!$C$4:$C$3247,A82),C82)) -> 30927.975 | E82: =B82-D82 -> -13655.595 | F82: =IF(D82=0,0,E82/D82) -> -0.4415289 | G82: =SUMIFS('Department Weekly'!$G$4:$G$3247,'Department Weekly'!$C$4:$C$3247,A82) -> 30027.16 | H82: =IF(E82>=0,"Favorable","Unfavorable") -> Unfavorable

Sheet Monthly History
A1: Monthly Historical Sales | B1: Monthly Historical Sales | C1: Monthly Historical Sales
A2: Monthly Historical Sales | B2: Monthly Historical Sales | C2: Monthly Historical Sales
A3: All weekly source rows | February 2010-October 2012
A4: Month | B4: Actual Sales | C4: Records
A5: 40210 | B5: 1.9033298e+08 | C5: 11839
A6: 40238 | B6: 1.819198e+08 | C6: 11788
A7: 40269 | B7: 2.3141237e+08 | C7: 14697
A8: 40299 | B8: 1.8671093e+08 | C8: 11672
A9: 40330 | B9: 1.9224617e+08 | C9: 11661
A10: 40360 | B10: 2.3258013e+08 | C10: 14561
A11: 40391 | B11: 1.8764011e+08 | C11: 11603
A12: 40422 | B12: 1.772679e+08 | C12: 11724
A13: 40452 | B13: 2.1716182e+08 | C13: 14667
A14: 40483 | B14: 2.0285337e+08 | C14: 11712
A15: 40513 | B15: 2.8876053e+08 | C15: 14755
A16: 40544 | B16: 1.6370397e+08 | C16: 11695
... A37: 41183 | B37: 1.8436168e+08 | C37: 11875

Sheet Store Weekly
A1: Store-Level Weekly Source and Scenario Calculations
A3: Date | B3: Month | C3: Store | D3: Store Type | E3: Store Size | F3: Holiday | G3: Actual Sales | H3: Prior-Year Sales | I3: Forecast Sales | J3: Base Plan | K3: Upside Plan | L3: Downside Plan
A4: 40914 | B4: 40909 | C4: 1 | D4: A | E4: 151315 | F4: No | G4: 1550369.9 | H4: 1444732.3 | I4: 1444732.3 | J4: =H4*(1+Assumptions!$B$6+IF(F4="Yes",Assumptions!$C$6,0)) -> 1488074.2 | K4: =H4*(1+Assumptions!$B$7+IF(F4="Yes",Assumptions!$C$7,0)) -> 1516968.9 | L4: =H4*(1+Assumptions!$B$8+IF(F4="Yes",Assumptions!$C$8,0)) -> 1459179.6
A5: 40914 | B5: 40909 | C5: 2 | D5: A | E5: 202307 | F5: No | G5: 1799520.1 | H5: 1758050.8 | I5: 1758050.8 | J5: =H5*(1+Assumptions!$B$6+IF(F5="Yes",Assumptions!$C$6,0)) -> 1810792.3 | K5: =H5*(1+Assumptions!$B$7+IF(F5="Yes",Assumptions!$C$7,0)) -> 1845953.3 | L5: =H5*(1+Assumptions!$B$8+IF(F5="Yes",Assumptions!$C$8,0)) -> 1775631.3
A6: 40914 | B6: 40909 | C6: 3 | D6: B | E6: 37392 | F6: No | G6: 397940.27 | H6: 378237.34 | I6: 378237.34 | J6: =H6*(1+Assumptions!$B$6+IF(F6="Yes",Assumptions!$C$6,0)) -> 389584.46 | K6: =H6*(1+Assumptions!$B$7+IF(F6="Yes",Assumptions!$C$7,0)) -> 397149.21 | L6: =H6*(1+Assumptions!$B$8+IF(F6="Yes",Assumptions!$C$8,0)) -> 382019.71
A7: 40914 | B7: 40909 | C7: 4 | D7: A | E7: 205863 | F7: No | G7: 2047854.1 | H7: 1862476.3 | I7: 1862476.3 | J7: =H7*(1+Assumptions!$B$6+IF(F7="Yes",Assumptions!$C$6,0)) -> 1918350.6 | K7: =H7*(1+Assumptions!$B$7+IF(F7="Yes",Assumptions!$C$7,0)) -> 1955600.1 | L7: =H7*(1+Assumptions!$B$8+IF(F7="Yes",Assumptions!$C$8,0)) -> 1881101
A8: 40914 | B8: 40909 | C8: 5 | D8: B | E8: 34875 | F8: No | G8: 311949.98 | H8: 285903.09 | I8: 285903.09 | J8: =H8*(1+Assumptions!$B$6+IF(F8="Yes",Assumptions!$C$6,0)) -> 294480.18 | K8: =H8*(1+Assumptions!$B$7+IF(F8="Yes",Assumptions!$C$7,0)) -> 300198.24 | L8: =H8*(1+Assumptions!$B$8+IF(F8="Yes",Assumptions!$C$8,0)) -> 288762.12
A9: 40914 | B9: 40909 | C9: 6 | D9: A | E9: 202505 | F9: No | G9: 1395339.7 | H9: 1350407.3 | I9: 1350407.3 | J9: =H9*(1+Assumptions!$B$6+IF(F9="Yes",Assumptions!$C$6,0)) -> 1390919.5 | K9: =H9*(1+Assumptions!$B$7+IF(F9="Yes",Assumptions!$C$7,0)) -> 1417927.6 | L9: =H9*(1+Assumptions!$B$8+IF(F9="Yes",Assumptions!$C$8,0)) -> 1363911.3
A10: 40914 | B10: 40909 | C10: 7 | D10: B | E10: 70713 | F10: No | G10: 711831.09 | H10: 661092.1 | I10: 661092.1 | J10: =H10*(1+Assumptions!$B$6+IF(F10="Yes",Assumptions!$C$6,0)) -> 680924.86 | K10: =H10*(1+Assumptions!$B$7+IF(F10="Yes",Assumptions!$C$7,0)) -> 694146.7 | L10: =H10*(1+Assumptions!$B$8+IF(F10="Yes",Assumptions!$C$8,0)) -> 667703.02
A11: 40914 | B11: 40909 | C11: 8 | D11: A | E11: 155078 | F11: No | G11: 872028.85 | H11: 873065.23 | I11: 873065.23 | J11: =H11*(1+Assumptions!$B$6+IF(F11="Yes",Assumptions!$C$6,0)) -> 899257.19 | K11: =H11*(1+Assumptions!$B$7+IF(F11="Yes",Assumptions!$C$7,0)) -> 916718.49 | L11: =H11*(1+Assumptions!$B$8+IF(F11="Yes",Assumptions!$C$8,0)) -> 881795.88
A12: 40914 | B12: 40909 | C12: 9 | D12: B | E12: 125833 | F12: No | G12: 518803.3 | H12: 490982.78 | I12: 490982.78 | J12: =H12*(1+Assumptions!$B$6+IF(F12="Yes",Assumptions!$C$6,0)) -> 505712.26 | K12: =H12*(1+Assumptions!$B$7+IF(F12="Yes",Assumptions!$C$7,0)) -> 515531.92 | L12: =H12*(1+Assumptions!$B$8+IF(F12="Yes",Assumptions!$C$8,0)) -> 495892.61
A13: 40914 | B13: 40909 | C13: 10 | D13: B | E13: 126512 | F13: No | G13: 1682572.8 | H13: 1714337.1 | I13: 1714337.1 | J13: =H13*(1+Assumptions!$B$6+IF(F13="Yes",Assumptions!$C$6,0)) -> 1765767.2 | K13: =H13*(1+Assumptions!$B$7+IF(F13="Yes",Assumptions!$C$7,0)) -> 1800053.9 | L13: =H13*(1+Assumptions!$B$8+IF(F13="Yes",Assumptions!$C$8,0)) -> 1731480.4
A14: 40914 | B14: 40909 | C14: 11 | D14: A | E14: 207499 | F14: No | G14: 1282525.7 | H14: 1178905.4 | I14: 1178905.4 | J14: =H14*(1+Assumptions!$B$6+IF(F14="Yes",Assumptions!$C$6,0)) -> 1214272.6 | K14: =H14*(1+Assumptions!$B$7+IF(F14="Yes",Assumptions!$C$7,0)) -> 1237850.7 | L14: =H14*(1+Assumptions!$B$8+IF(F14="Yes",Assumptions!$C$8,0)) -> 1190694.5
A15: 40914 | B15: 40909 | C15: 12 | D15: B | E15: 112238 | F15: No | G15: 945793.95 | H15: 910110.24 | I15: 910110.24 | J15: =H15*(1+Assumptions!$B$6+IF(F15="Yes",Assumptions!$C$6,0)) -> 937413.55 | K15: =H15*(1+Assumptions!$B$7+IF(F15="Yes",Assumptions!$C$7,0)) -> 955615.75 | L15: =H15*(1+Assumptions!$B$8+IF(F15="Yes",Assumptions!$C$8,0)) -> 919211.34
... A1938: 41208 | B1938: 41183 | C1938: 45 | D1938: B | E1938: 118221 | F1938: No | G1938: 760257.51 | H1938: 781647.05 | I1938: 781647.05 | J1938: =H1938*(1+Assumptions!$B$6+IF(F1938="Yes",Assumptions!$C$6,0)) -> 805096.46 | K1938: =H1938*(1+Assumptions!$B$7+IF(F1938="Yes",Assumptions!$C$7,0)) -> 820729.4 | L1938: =H1938*(1+Assumptions!$B$8+IF(F1938="Yes",Assumptions!$C$8,0)) -> 789463.52

Sheet Department Weekly
A1: Department-Level Weekly Source and Scenario Calculations
A3: Date | B3: Month | C3: Department | D3: Holiday | E3: Actual Sales | F3: Prior-Year Sales | G3: Forecast Sales | H3: Base Plan | I3: Upside Plan | J3: Downside Plan
A4: 40914 | B4: 40909 | C4: 1 | D4: No | E4: 593103.91 | F4: 523274.28 | G4: 523274.28 | H4: =F4*(1+Assumptions!$B$6+IF(D4="Yes",Assumptions!$C$6,0)) -> 538972.51 | I4: =F4*(1+Assumptions!$B$7+IF(D4="Yes",Assumptions!$C$7,0)) -> 549437.99 | J4: =F4*(1+Assumptions!$B$8+IF(D4="Yes",Assumptions!$C$8,0)) -> 528507.02
A5: 40914 | B5: 40909 | C5: 2 | D5: No | E5: 1936413.7 | F5: 1799906.3 | G5: 1799906.3 | H5: =F5*(1+Assumptions!$B$6+IF(D5="Yes",Assumptions!$C$6,0)) -> 1853903.5 | I5: =F5*(1+Assumptions!$B$7+IF(D5="Yes",Assumptions!$C$7,0)) -> 1889901.6 | J5: =F5*(1+Assumptions!$B$8+IF(D5="Yes",Assumptions!$C$8,0)) -> 1817905.4
A6: 40914 | B6: 40909 | C6: 3 | D6: No | E6: 525514.59 | F6: 549175.36 | G6: 549175.36 | H6: =F6*(1+Assumptions!$B$6+IF(D6="Yes",Assumptions!$C$6,0)) -> 565650.62 | I6: =F6*(1+Assumptions!$B$7+IF(D6="Yes",Assumptions!$C$7,0)) -> 576634.13 | J6: =F6*(1+Assumptions!$B$8+IF(D6="Yes",Assumptions!$C$8,0)) -> 554667.11
A7: 40914 | B7: 40909 | C7: 4 | D7: No | E7: 1312275.5 | F7: 1222500.8 | G7: 1222500.8 | H7: =F7*(1+Assumptions!$B$6+IF(D7="Yes",Assumptions!$C$6,0)) -> 1259175.8 | I7: =F7*(1+Assumptions!$B$7+IF(D7="Yes",Assumptions!$C$7,0)) -> 1283625.8 | J7: =F7*(1+Assumptions!$B$8+IF(D7="Yes",Assumptions!$C$8,0)) -> 1234725.8
A8: 40914 | B8: 40909 | C8: 5 | D8: No | E8: 797274.53 | F8: 852362.54 | G8: 852362.54 | H8: =F8*(1+Assumptions!$B$6+IF(D8="Yes",Assumptions!$C$6,0)) -> 877933.42 | I8: =F8*(1+Assumptions!$B$7+IF(D8="Yes",Assumptions!$C$7,0)) -> 894980.67 | J8: =F8*(1+Assumptions!$B$8+IF(D8="Yes",Assumptions!$C$8,0)) -> 860886.17
A9: 40914 | B9: 40909 | C9: 6 | D9: No | E9: 114623.36 | F9: 126756.18 | G9: 126756.18 | H9: =F9*(1+Assumptions!$B$6+IF(D9="Yes",Assumptions!$C$6,0)) -> 130558.87 | I9: =F9*(1+Assumptions!$B$7+IF(D9="Yes",Assumptions!$C$7,0)) -> 133093.99 | J9: =F9*(1+Assumptions!$B$8+IF(D9="Yes",Assumptions!$C$8,0)) -> 128023.74
A10: 40914 | B10: 40909 | C10: 7 | D10: No | E10: 567023.85 | F10: 538596.79 | G10: 538596.79 | H10: =F10*(1+Assumptions!$B$6+IF(D10="Yes",Assumptions!$C$6,0)) -> 554754.69 | I10: =F10*(1+Assumptions!$B$7+IF(D10="Yes",Assumptions!$C$7,0)) -> 565526.63 | J10: =F10*(1+Assumptions!$B$8+IF(D10="Yes",Assumptions!$C$8,0)) -> 543982.76
A11: 40914 | B11: 40909 | C11: 8 | D11: No | E11: 1326346.7 | F11: 1322007.9 | G11: 1322007.9 | H11: =F11*(1+Assumptions!$B$6+IF(D11="Yes",Assumptions!$C$6,0)) -> 1361668.1 | I11: =F11*(1+Assumptions!$B$7+IF(D11="Yes",Assumptions!$C$7,0)) -> 1388108.3 | J11: =F11*(1+Assumptions!$B$8+IF(D11="Yes",Assumptions!$C$8,0)) -> 1335227.9
A12: 40914 | B12: 40909 | C12: 9 | D12: No | E12: 571869.16 | F12: 504120.1 | G12: 504120.1 | H12: =F12*(1+Assumptions!$B$6+IF(D12="Yes",Assumptions!$C$6,0)) -> 519243.7 | I12: =F12*(1+Assumptions!$B$7+IF(D12="Yes",Assumptions!$C$7,0)) -> 529326.1 | J12: =F12*(1+Assumptions!$B$8+IF(D12="Yes",Assumptions!$C$8,0)) -> 509161.3
A13: 40914 | B13: 40909 | C13: 10 | D13: No | E13: 734989.76 | F13: 700428.13 | G13: 700428.13 | H13: =F13*(1+Assumptions!$B$6+IF(D13="Yes",Assumptions!$C$6,0)) -> 721440.97 | I13: =F13*(1+Assumptions!$B$7+IF(D13="Yes",Assumptions!$C$7,0)) -> 735449.54 | J13: =F13*(1+Assumptions!$B$8+IF(D13="Yes",Assumptions!$C$8,0)) -> 707432.41
A14: 40914 | B14: 40909 | C14: 11 | D14: No | E14: 656927.92 | F14: 651976.55 | G14: 651976.55 | H14: =F14*(1+Assumptions!$B$6+IF(D14="Yes",Assumptions!$C$6,0)) -> 671535.85 | I14: =F14*(1+Assumptions!$B$7+IF(D14="Yes",Assumptions!$C$7,0)) -> 684575.38 | J14: =F14*(1+Assumptions!$B$8+IF(D14="Yes",Assumptions!$C$8,0)) -> 658496.32
A15: 40914 | B15: 40909 | C15: 12 | D15: No | E15: 137351.55 | F15: 120904.85 | G15: 120904.85 | H15: =F15*(1+Assumptions!$B$6+IF(D15="Yes",Assumptions!$C$6,0)) -> 124532 | I15: =F15*(1+Assumptions!$B$7+IF(D15="Yes",Assumptions!$C$7,0)) -> 126950.09 | J15: =F15*(1+Assumptions!$B$8+IF(D15="Yes",Assumptions!$C$8,0)) -> 122113.9
... A3247: 41208 | B3247: 41183 | C3247: 98 | D3247: No | E3247: 302469.28 | F3247: 314747.82 | G3247: 314747.82 | H3247: =F3247*(1+Assumptions!$B$6+IF(D3247="Yes",Assumptions!$C$6,0)) -> 324190.25 | I3247: =F3247*(1+Assumptions!$B$7+IF(D3247="Yes",Assumptions!$C$7,0)) -> 330485.21 | J3247: =F3247*(1+Assumptions!$B$8+IF(D3247="Yes",Assumptions!$C$8,0)) -> 317895.3

Sheet Checks & Sources
A1: Model Checks and Sources | B1: Model Checks and Sources | C1: Model Checks and Sources | D1: Model Checks and Sources | E1: Model Checks and Sources | F1: Model Checks and Sources | G1: Model Checks and Sources
A2: Model Checks and Sources | B2: Model Checks and Sources | C2: Model Checks and Sources | D2: Model Checks and Sources | E2: Model Checks and Sources | F2: Model Checks and Sources | G2: Model Checks and Sources
A4: Check | B4: Actual | C4: Expected | D4: Difference | E4: Tolerance | F4: Status | G4: Where to Fix
A5: Store actuals tie to published total | B5: =SUM('Store Weekly'!$G$4:$G$1938) -> 1.9992655e+09 | C5: 1.9992655e+09 | D5: =ROUND(B5-C5,2) -> 0 | E5: 1 | F5: =IF(ABS(D5)<=E5,1,0) -> 1 | G5: Store Weekly
A6: Department actuals tie to store actuals | B6: =SUM('Department Weekly'!$E$4:$E$3247) -> 1.9992655e+09 | C6: =B5 -> 1.9992655e+09 | D6: =ROUND(B6-C6,2) -> 0 | E6: 0.01 | F6: =IF(ABS(D6)<=E6,1,0) -> 1 | G6: Department Weekly
A7: Base plan ties to published total | B7: =SUM('Store Weekly'!$J$4:$J$1938) -> 2.0082227e+09 | C7: 2.0082227e+09 | D7: =ROUND(B7-C7,2) -> 0 | E7: 1 | F7: =IF(ABS(D7)<=E7,1,0) -> 1 | G7: Assumptions / Store Weekly
A8: Monthly actuals tie to store actuals | B8: ='Scenario Summary'!B16 -> 1.9992655e+09 | C8: =B5 -> 1.9992655e+09 | D8: =ROUND(B8-C8,2) -> 0 | E8: 0.01 | F8: =IF(ABS(D8)<=E8,1,0) -> 1 | G8: Scenario Summary
A9: Scenario selector is valid | B9: =IF(OR(Assumptions!$B$10="Base",Assumptions!$B$10="Upside",Assumptions!$B$10="Downside"),1,0) -> 1 | C9: 1 | D9: =ROUND(B9-C9,2) -> 0 | E9: 0.01 | F9: =IF(ABS(D9)<=E9,1,0) -> 1 | G9: Assumptions B10
A10: No blank scenario assumption cells | B10: =COUNT(Assumptions!$B$6:$C$8) -> 6 | C10: 6 | D10: =ROUND(B10-C10,2) -> 0 | E10: 0.01 | F10: =IF(ABS(D10)<=E10,1,0) -> 1 | G10: Assumptions B6:C8
A12: MODEL STATUS | B12: =IF(AND(COUNT(F5:F10)=6,SUM(F5:F10)=6),1,0) -> 1
A15: Item | B15: Value | C15: Units | D15: Period / As Of | E15: Source Type | F15: Source / URL | G15: Notes
A16: Weekly sales source | B16: 421570 | C16: Rows | D16: 2010-02-05 to 2012-10-26 | E16: Competition dataset | F16: https://www.kaggle.com/c/walmart-recruiting-store-sales-forecasting | G16: Raw train, features, and stores files
A17: Evaluation actual sales | B17: 1.9992655e+09 | C17: USD | D17: Jan-Oct 2012 | E17: Python pipeline | F17: python/pipeline.py | G17: Published Power BI total
A18: Base planning scenario | B18: 2.0082227e+09 | C18: USD | D18: Jan-Oct 2012 | E18: Python pipeline | F18: python/pipeline.py | G18: Prior-year comparable week plus 3%
A19: Forecast MAE | B19: 1811.56 | C19: USD per row | D19: Jan-Oct 2012 | E19: Python pipeline | F19: data/processed/forecast_metrics.csv | G19: Seasonal naive
A20: Forecast WMAE | B20: 1818.03 | C20: USD per row | D20: Jan-Oct 2012 | E20: Python pipeline | F20: data/processed/forecast_metrics.csv | G20: Holiday errors weighted 5x
A21: Planning disclaimer | B21: Illustrative | C21: Method | D21: 2012 | E21: Project methodology | F21: README.md | G21: Not Walmart internal budget or target
